CHANGES.txt
LICENSE.txt
MANIFEST.in
README.txt
setup.cfg
setup.py
PyBeanstream.egg-info/PKG-INFO
PyBeanstream.egg-info/SOURCES.txt
PyBeanstream.egg-info/dependency_links.txt
PyBeanstream.egg-info/namespace_packages.txt
PyBeanstream.egg-info/requires.txt
PyBeanstream.egg-info/top_level.txt
pybeanstream/__init__.py
pybeanstream/classes.py
pybeanstream/client.py
pybeanstream/tests.py
pybeanstream/xml_utils.py