Metadata-Version: 1.1
Name: PyBeanstream
Version: 0.5
Summary: Payment module to talk with the Beanstream API
Home-page: http://bitbucket.org/benoitcsirois/pybeanstream/
Author: Benoit C. Sirois
Author-email: benoitcsirois@gmail.com
License: LICENSE.txt
Platform: UNKNOWN
Classifier: Programming Language :: Python
Classifier: Topic :: Office/Business
Classifier: Intended Audience :: Developers
Classifier: License :: OSI Approved :: GNU Library or Lesser General Public License (LGPL)
